wandb/__init__.py
wandb/__main__.py
wandb/data_types.py
wandb/env.py
wandb/jupyter.py
wandb/magic.py
wandb/py.typed
wandb/trigger.py
wandb/util.py
wandb/viz.py
wandb/wandb_agent.py
wandb/wandb_controller.py
wandb/wandb_run.py
wandb/wandb_torch.py
wandb/apis/__init__.py
wandb/apis/internal.py
wandb/apis/internal_runqueue.py
wandb/apis/normalize.py
wandb/apis/public.py
wandb/backend/__init__.py
wandb/backend/backend.py
wandb/cli/__init__.py
wandb/cli/cli.py
wandb/compat/__init__.py
wandb/compat/tempfile.py
wandb/compat/weakref.py
wandb/docker/__init__.py
wandb/docker/auth.py
wandb/docker/wandb-entrypoint.sh
wandb/docker/www_authenticate.py
wandb/errors/__init__.py
wandb/errors/error.py
wandb/errors/term.py
wandb/fastai/__init__.py
wandb/filesync/__init__.py
wandb/filesync/dir_watcher.py
wandb/filesync/stats.py
wandb/filesync/step_checksum.py
wandb/filesync/step_prepare.py
wandb/filesync/step_upload.py
wandb/filesync/upload_job.py
wandb/integration/__init__.py
wandb/integration/magic.py
wandb/integration/fastai/__init__.py
wandb/integration/gym/__init__.py
wandb/integration/keras/__init__.py
wandb/integration/keras/keras.py
wandb/integration/lightgbm/__init__.py
wandb/integration/sagemaker/__init__.py
wandb/integration/sagemaker/auth.py
wandb/integration/sagemaker/config.py
wandb/integration/sagemaker/files.py
wandb/integration/sagemaker/resources.py
wandb/integration/tensorboard/__init__.py
wandb/integration/tensorboard/log.py
wandb/integration/tensorboard/monkeypatch.py
wandb/integration/tensorflow/__init__.py
wandb/integration/tensorflow/estimator_hook.py
wandb/integration/torch/__init__.py
wandb/integration/xgboost/__init__.py
wandb/interface/__init__.py
wandb/interface/artifacts.py
wandb/interface/constants.py
wandb/interface/interface.py
wandb/interface/summary_record.py
wandb/internal/__init__.py
wandb/internal/artifacts.py
wandb/internal/datastore.py
wandb/internal/file_pusher.py
wandb/internal/file_stream.py
wandb/internal/handler.py
wandb_ng-0.0.44.dist-info/METADATA
wandb_ng-0.0.44.dist-info/WHEEL
wandb_ng-0.0.44.dist-info/entry_points.txt
wandb_ng-0.0.44.dist-info/top_level.txt
wandb_ng-0.0.44.dist-info/RECORD
