Metadata-Version: 2.1
Name: wandb-ng
Version: 0.0.44
Summary: A CLI and library for interacting with the Weights and Biases API.
Home-page: https://github.com/wandb/client
Author: Weights & Biases
Author-email: support@wandb.com
License: MIT license
Platform: UNKNOWN
Classifier: Development Status :: 5 - Production/Stable
Classifier: Intended Audience :: Developers
Classifier: Intended Audience :: Science/Research
Classifier: License :: OSI Approved :: MIT License
Classifier: Natural Language :: English
Classifier: Programming Language :: Python :: 2
Classifier: Programming Language :: Python :: 2.7
Classifier: Programming Language :: Python :: 3
Classifier: Programming Language :: Python :: 3.4
Classifier: Programming Language :: Python :: 3.5
Classifier: Programming Language :: Python :: 3.6
Classifier: Programming Language :: Python :: 3.7
Classifier: Topic :: Scientific/Engineering :: Artificial Intelligence
Classifier: Topic :: Software Development :: Libraries :: Python Modules
Classifier: Topic :: System :: Logging
Classifier: Topic :: System :: Monitoring
Requires-Python: >=2.7, !=3.0.*, !=3.1.*, !=3.2.*, !=3.3.*
Requires-Dist: Click (>=7.0)
Requires-Dist: GitPython (>=1.0.0)
Requires-Dist: python-dateutil (>=2.6.1)
Requires-Dist: requests (<3,>=2.0.0)
Requires-Dist: promise (<3,>=2.0)
Requires-Dist: shortuuid (>=0.5.0)
Requires-Dist: six (>=1.13.0)
Requires-Dist: watchdog (>=0.8.3)
Requires-Dist: psutil (>=5.0.0)
Requires-Dist: sentry-sdk (>=0.4.0)
Requires-Dist: subprocess32 (>=3.5.3)
Requires-Dist: docker-pycreds (>=0.4.0)
Requires-Dist: configparser (>=3.8.1)
Requires-Dist: protobuf (>=3.12.0)
Requires-Dist: PyYAML
Requires-Dist: enum34 ; python_version < "3.4"
Requires-Dist: typing ; python_version < "3.5"
Provides-Extra: aws
Requires-Dist: boto3 ; extra == 'aws'
Provides-Extra: gcp
Requires-Dist: google-cloud-storage ; extra == 'gcp'
Provides-Extra: grpc
Requires-Dist: grpcio (==1.27.2) ; extra == 'grpc'
Provides-Extra: kubeflow
Requires-Dist: kubernetes ; extra == 'kubeflow'
Requires-Dist: minio ; extra == 'kubeflow'
Requires-Dist: google-cloud-storage ; extra == 'kubeflow'
Requires-Dist: sh ; extra == 'kubeflow'
